miniset/__init__.py
miniset/exceptions.py
miniset/extensions.py
miniset/filters.py
miniset/jinja_context.py
miniset/types.py
mini_set-0.3.0.dist-info/METADATA
mini_set-0.3.0.dist-info/WHEEL
mini_set-0.3.0.dist-info/licenses/LICENSE
mini_set-0.3.0.dist-info/RECORD
