Metadata-Version: 2.4
Name: mini-set
Version: 0.3.0
Summary: A Jinja2 template processor for interacting with an SQL engine
Project-URL: Homepage, https://github.com/ninoseki/miniset
Project-URL: Repository, https://github.com/ninoseki/miniset
Project-URL: Documentation, https://ninoseki.github.io/miniset/
Author-email: Manabu Niseki <manabu.niseki@gmail.com>
License-File: LICENSE
Requires-Python: <4.0,>=3.9
Requires-Dist: jinja2~=3.1
